{
  "main": {
    "id": "e21ee2768821a123",
    "type": "split",
    "children": [
      {
        "id": "a9fcd3bda353dd5b",
        "type": "tabs",
        "children": [
          {
            "id": "7e253b984fd1cf6e",
            "type": "leaf",
            "state": {
              "type": "markdown",
              "state": {
                "file": "ssh/pldc/new/law/law src.md",
                "mode": "source",
                "source": false
              }
            }
          },
          {
            "id": "2023d3747750f2f8",
            "type": "leaf",
            "state": {
              "type": "markdown",
              "state": {
                "file": "ssh/ktct/new/compete/thi.md",
                "mode": "source",
                "source": false
              }
            }
          }
        ]
      }
    ],
    "direction": "vertical"
  },
  "left": {
    "id": "f366f6f81606f81b",
    "type": "split",
    "children": [
      {
        "id": "81e5f3388fc6606b",
        "type": "tabs",
        "children": [
          {
            "id": "bd9349628f37c85c",
            "type": "leaf",
            "state": {
              "type": "file-explorer",
              "state": {
                "sortOrder": "alphabetical"
              }
            }
          },
          {
            "id": "55acd4f35babc256",
            "type": "leaf",
            "state": {
              "type": "search",
              "state": {
                "query": "agricul",
                "matchingCase": false,
                "explainSearch": false,
                "collapseAll": false,
                "extraContext": false,
                "sortOrder": "alphabetical"
              }
            }
          },
          {
            "id": "71e116857e17feb4",
            "type": "leaf",
            "state": {
              "type": "bookmarks",
              "state": {}
            }
          }
        ]
      }
    ],
    "direction": "horizontal",
    "width": 300
  },
  "right": {
    "id": "f1fb825814246907",
    "type": "split",
    "children": [
      {
        "id": "ba67bd4969c5d563",
        "type": "tabs",
        "children": [
          {
            "id": "c4baece6a639f018",
            "type": "leaf",
            "state": {
              "type": "backlink",
              "state": {
                "file": "ssh/pldc/new/law/law src.md",
                "collapseAll": false,
                "extraContext": false,
                "sortOrder": "alphabetical",
                "showSearch": false,
                "searchQuery": "",
                "backlinkCollapsed": false,
                "unlinkedCollapsed": true
              }
            }
          },
          {
            "id": "a2dcb799075d9e5a",
            "type": "leaf",
            "state": {
              "type": "advanced-tables-toolbar",
              "state": {}
            }
          }
        ],
        "currentTab": 1
      }
    ],
    "direction": "horizontal",
    "width": 300,
    "collapsed": true
  },
  "left-ribbon": {
    "hiddenItems": {
      "switcher:Open quick switcher": false,
      "graph:Open graph view": false,
      "canvas:Create new canvas": false,
      "command-palette:Open command palette": false,
      "markdown-importer:Open format converter": false,
      "table-editor-obsidian:Advanced Tables Toolbar": false,
      "obsidian-excalidraw-plugin:Create new drawing": false,
      "janitor:Janitor: scan vault": false
    }
  },
  "active": "7e253b984fd1cf6e",
  "lastOpenFiles": [
    "ssh/ktct/new/compete/thi.md",
    "ssh/pldc/new/law/law src.md",
    "ssh/pldc/new/law/law form.md",
    "ssh/pldc/new/law/law norms.md",
    "ssh/ktct/new/compete/monopoly.md",
    "ssh/pldc/new/law/law.md",
    "ssh/pldc/new/law/law execution.md",
    "ssh/pldc/new/state/state forms.md",
    "ssh/pldc/new/state/state.md",
    "ssh/pldc/new/state/primitive communism.md",
    "ssh/pldc/new/state/marxian state src.md",
    "ssh/pldc/new/state/idealist state src.md",
    "maths/calc2/integrals/surfaceint.md",
    "maths/calc2/fields/scalar potential.md",
    "maths/calc2/integrals/lineint.md",
    "maths/calc2/fields/field.md",
    "maths/calc2/fields/ext derv.md",
    "maths/calc2/fields/directional.md",
    "maths/calc2/fields/circulation.md",
    "maths/calc2/gstoke/generalized stoke's theorem.md",
    "ssh/pldc/vppl & tnpl.md",
    "maths/calc3/laplace/laplace.md",
    "ssh/pldc/new/state/src.md",
    "ssh/pldc/state/type.md",
    "ssh/pldc/state/source.md",
    "ssh/pldc/state/nature.md",
    "assets/Pasted image 20230703181018.png",
    "assets/Pasted image 20230703181004.png",
    "assets/Pasted image 20230703180926.png",
    "ssh/pldc/new/law",
    "ssh/ktct/new/compete",
    "ssh/ktct/new/surplus",
    "assets/Pasted image 20230614145248.png",
    "assets/Pasted image 20230614144323.png",
    "ssh/ktct/new/market",
    "ssh/ktct/new/money",
    "ssh/ktct/new/intro",
    "ssh/ktct/new/commodity",
    "ssh/ktct/new",
    "maths/calc3/laplace",
    "ssh/ktct/surplus",
    "assets/Pasted image 20230515162702.png",
    "assets/Pasted image 20230425133208.png",
    "assets/Pasted image 20230425130043.png",
    "assets/Pasted image 20230425124522.png",
    "assets/Pasted image 20230425124314.png",
    "Untitled.canvas"
  ]
}